[
  {
    "Name": "Szpoti",
    "Elo": 100
  },
  {
    "Name": "Dani",
    "Elo": 200
  },
  {
    "Name": "Clement",
    "Elo": 300
  },
  {
    "Name": "Roland",
    "Elo": 200
  },
  {
    "Name": "Marnix",
    "Elo": 200
  },
  {
    "Name": "Thib",
    "Elo": 200
  },
  {
    "Name": "David",
    "Elo": 200
  },
  {
    "Name": "Adam",
    "Elo": 200
  },
  {
    "Name": "Rafe",
    "Elo": 200
  },
  {
    "Name": "Max",
    "Elo": 200
  },
  {
    "Name": "Szabolcs",
    "Elo": 200
  },
  {
    "Name": "Lucas",
    "Elo": 200
  },
]